{
  "projects": [
    {
      "name": "testing f",
      "budget": "1244",
      "category": {
        "id": "2",
        "name": "Development"
      },
      "cost": 12,
      "services": [
        {
          "name": "my new service",
          "cost": "12",
          "description": "asdfasdf",
          "id": "9fa31423-c8fb-4a01-ab8a-e20c008bec6e"
        }
      ],
      "id": 1
    }
  ],
  "categories": [
    {
      "id": 1,
      "name": "Infrastructure"
    },
    {
      "id": 2,
      "name": "Development"
    },
    {
      "id": 3,
      "name": "Design"
    },
    {
      "id": 4,
      "name": "Marketing"
    }
  ]
}